embrs/embrs/__init__.py
embrs/embrs/main.py
embrs/embrs/map_generator.py
embrs/embrs/visualization_tool.py
embrs/embrs/wind_forecast_generator.py
embrs/embrs/base_classes/__init__.py
embrs/embrs/base_classes/agent_base.py
embrs/embrs/base_classes/base_fire.py
embrs/embrs/base_classes/control_base.py
embrs/embrs/fire_simulator/__init__.py
embrs/embrs/fire_simulator/cell.py
embrs/embrs/fire_simulator/fire.py
embrs/embrs/fire_simulator/fuel.py
embrs/embrs/fire_simulator/logger.py
embrs/embrs/fire_simulator/visualizer.py
embrs/embrs/fire_simulator/wind.py
embrs/embrs/tools/__init__.py
embrs/embrs/tools/fire_predictor.py
embrs/embrs/utilities/__init__.py
embrs/embrs/utilities/action.py
embrs/embrs/utilities/file_io.py
embrs/embrs/utilities/fire_colors.py
embrs/embrs/utilities/fire_util.py
embrs/embrs/utilities/fuel_colors.py
embrs/embrs/utilities/fuel_content_colors.py
embrs/embrs/utilities/map_drawer.py
embrs/embrs/utilities/road_colors.py
embrs/embrs/utilities/spread_prob_table_generator.py
embrs/examples/__init__.py
embrs/examples/i_interpretting_sim_logs.py
embrs/examples/ii_embrs_interface.py
embrs/examples/iii_custom_logging.py
embrs/examples/iv_fire_prediction_model.py
embrs/examples/v_sample_agent.py
embrs/examples/vi_controlled_burning.py
embrs/examples/vii_suppression.py
embrs/sample_raw_map_data/sample.py
embrs-0.0.18.dist-info/METADATA
embrs-0.0.18.dist-info/WHEEL
embrs-0.0.18.dist-info/entry_points.txt
embrs-0.0.18.dist-info/top_level.txt
embrs-0.0.18.dist-info/RECORD
